{
  "slug": "ce-foundation-engineering",
  "name": "Foundation Engineering",
  "questions": [
    {
      "id": "ce-fe-001",
      "subject": "Foundation Engineering",
      "topic": "Bearing Pressure",
      "difficulty": "medium",
      "type": "NAT",
      "stem": "A footing applies a gross pressure of $200\\,\\text{kPa}$ at depth $1.5\\,\\text{m}$ ($\\gamma=18\\,\\text{kN/m}^3$). The net pressure is _____ kPa.",
      "answer": 173,
      "tolerance": 0.1,
      "solution": "**Concept.** $q_{net}=q_{gross}-\\gamma D_f$.\n\n**Working.**\n$$q_{net}=200-18\\times 1.5=173.$$\n\n**Answer.** $173\\,\\text{kPa}$",
      "archetype": "A",
      "marks": 1
    },
    {
      "id": "ce-fe-002",
      "subject": "Foundation Engineering",
      "topic": "Bearing Pressure",
      "difficulty": "medium",
      "type": "NAT",
      "stem": "A footing applies a gross pressure of $250\\,\\text{kPa}$ at depth $2\\,\\text{m}$ ($\\gamma=20\\,\\text{kN/m}^3$). The net pressure is _____ kPa.",
      "answer": 210,
      "tolerance": 0.1,
      "solution": "**Concept.** $q_{net}=q_{gross}-\\gamma D_f$.\n\n**Working.**\n$$q_{net}=250-20\\times 2=210.$$\n\n**Answer.** $210\\,\\text{kPa}$",
      "archetype": "A",
      "marks": 1
    },
    {
      "id": "ce-fe-003",
      "subject": "Foundation Engineering",
      "topic": "Terzaghi Bearing Capacity",
      "difficulty": "hard",
      "type": "NAT",
      "stem": "A strip footing rests at $1\\,\\text{m}$ depth on clay ($c=30\\,\\text{kPa}$, $\\phi=0$, $\\gamma=18\\,\\text{kN/m}^3$). Using Terzaghi ($N_c=5.7,\\ N_q=1,\\ N_\\gamma=0$), the ultimate bearing capacity is _____ kPa.",
      "answer": 189,
      "tolerance": 1,
      "solution": "**Concept.** $q_u=cN_c+\\gamma D_f N_q + 0.5\\gamma B N_\\gamma$ with $N_\\gamma=0$.\n\n**Working.**\n$$q_u=30\\times5.7+18\\times 1\\times1=189.$$\n\n**Answer.** $189\\,\\text{kPa}$",
      "archetype": "C",
      "marks": 2
    },
    {
      "id": "ce-fe-004",
      "subject": "Foundation Engineering",
      "topic": "Pile Foundations",
      "difficulty": "medium",
      "type": "MCQ",
      "stem": "The group efficiency of a pile group is generally defined as",
      "options": [
        "group capacity ÷ sum of individual pile capacities",
        "sum of pile capacities ÷ group capacity",
        "number of piles × single capacity",
        "settlement ratio"
      ],
      "answer": 0,
      "solution": "**Concept.** $\\eta_g=\\dfrac{Q_{group}}{n Q_{single}}$.\n\n**Working.**\nGroup/Σ individual.\n\n**Answer.** Group ÷ Σ individual",
      "archetype": "B",
      "marks": 1
    },
    {
      "id": "ce-fe-005",
      "subject": "Foundation Engineering",
      "topic": "Safe Bearing Capacity",
      "difficulty": "easy",
      "type": "NAT",
      "stem": "The ultimate bearing capacity is $300\\,\\text{kPa}$. With a factor of safety of $3$, the net safe bearing capacity (gross basis) is _____ kPa.",
      "answer": 100,
      "tolerance": 0.1,
      "solution": "**Concept.** $q_{safe}=\\dfrac{q_u}{\\text{FoS}}$.\n\n**Working.**\n$$q_{safe}=\\dfrac{300}{3}=100.$$\n\n**Answer.** $100\\,\\text{kPa}$",
      "archetype": "A",
      "marks": 1
    },
    {
      "id": "ce-fe-006",
      "subject": "Foundation Engineering",
      "topic": "Safe Bearing Capacity",
      "difficulty": "easy",
      "type": "NAT",
      "stem": "The ultimate bearing capacity is $450\\,\\text{kPa}$. With a factor of safety of $3$, the net safe bearing capacity (gross basis) is _____ kPa.",
      "answer": 150,
      "tolerance": 0.1,
      "solution": "**Concept.** $q_{safe}=\\dfrac{q_u}{\\text{FoS}}$.\n\n**Working.**\n$$q_{safe}=\\dfrac{450}{3}=150.$$\n\n**Answer.** $150\\,\\text{kPa}$",
      "archetype": "A",
      "marks": 1
    },
    {
      "id": "ce-fe-007",
      "subject": "Foundation Engineering",
      "topic": "Settlement",
      "difficulty": "medium",
      "type": "MCQ",
      "stem": "Immediate (elastic) settlement of a footing on saturated clay is computed using",
      "options": [
        "undrained modulus $E_u$ and $\\nu=0.5$",
        "drained modulus only",
        "consolidation theory",
        "$c_v$ and time factor"
      ],
      "answer": 0,
      "solution": "**Concept.** Immediate settlement uses $E_u$, $\\nu=0.5$ (no volume change).\n\n**Working.**\n$E_u$, $\\nu=0.5$.\n\n**Answer.** Undrained $E_u$, $\\nu=0.5$",
      "archetype": "B",
      "marks": 1
    },
    {
      "id": "ce-fe-008",
      "subject": "Foundation Engineering",
      "topic": "Earth Pressure",
      "difficulty": "medium",
      "type": "NAT",
      "stem": "For a cohesionless backfill with $\\phi=30^\\circ$, the Rankine active earth pressure coefficient $K_a$ is _____.",
      "answer": 0.3333,
      "tolerance": 0.01,
      "solution": "**Concept.** $K_a=\\dfrac{1-\\sin\\phi}{1+\\sin\\phi}$.\n\n**Working.**\n$$K_a=\\dfrac{1-\\sin 30^\\circ}{1+\\sin 30^\\circ}=0.333.$$\n\n**Answer.** $0.333$",
      "archetype": "A",
      "marks": 2
    },
    {
      "id": "ce-fe-009",
      "subject": "Foundation Engineering",
      "topic": "Earth Pressure",
      "difficulty": "medium",
      "type": "NAT",
      "stem": "For a cohesionless backfill with $\\phi=36^\\circ$, the Rankine active earth pressure coefficient $K_a$ is _____.",
      "answer": 0.2596,
      "tolerance": 0.01,
      "solution": "**Concept.** $K_a=\\dfrac{1-\\sin\\phi}{1+\\sin\\phi}$.\n\n**Working.**\n$$K_a=\\dfrac{1-\\sin 36^\\circ}{1+\\sin 36^\\circ}=0.26.$$\n\n**Answer.** $0.26$",
      "archetype": "A",
      "marks": 2
    },
    {
      "id": "ce-fe-010",
      "subject": "Foundation Engineering",
      "topic": "Earth Pressure — Passive",
      "difficulty": "medium",
      "marks": 2,
      "type": "NAT",
      "stem": "For a cohesionless soil with $\\phi=32^\\circ$, the Rankine passive earth pressure coefficient $K_p$ is _____.",
      "answer": 3.254588303299863,
      "tolerance": 0.01,
      "solution": "**Concept.** $K_p=\\dfrac{1+\\sin\\phi}{1-\\sin\\phi}$.\n\n**Working.**\n$$\\dfrac{1+\\sin32^\\circ}{1-\\sin32^\\circ}=3.255.$$\n\n**Answer.** $3.255$",
      "archetype": "A"
    },
    {
      "id": "ce-fe-011",
      "subject": "Foundation Engineering",
      "topic": "Earth Pressure — Passive",
      "difficulty": "medium",
      "marks": 2,
      "type": "NAT",
      "stem": "For a cohesionless soil with $\\phi=36^\\circ$, the Rankine passive earth pressure coefficient $K_p$ is _____.",
      "answer": 3.8518399963191827,
      "tolerance": 0.01,
      "solution": "**Concept.** $K_p=\\dfrac{1+\\sin\\phi}{1-\\sin\\phi}$.\n\n**Working.**\n$$\\dfrac{1+\\sin36^\\circ}{1-\\sin36^\\circ}=3.852.$$\n\n**Answer.** $3.852$",
      "archetype": "A"
    },
    {
      "id": "ce-fe-012",
      "subject": "Foundation Engineering",
      "topic": "Pile Capacity — Clay",
      "difficulty": "hard",
      "marks": 2,
      "type": "NAT",
      "stem": "A bored pile $0.5\\,\\text{m}$ dia, $10\\,\\text{m}$ long in clay ($c=60\\,\\text{kPa}$, $N_c=9$, $\\alpha=0.6$). Its ultimate capacity (end + skin) is _____ kN.",
      "answer": 671.5154297048183,
      "tolerance": 1,
      "solution": "**Concept.** $Q_u=9cA_p+\\alpha c A_s$.\n\n**Working.**\n$$9\\times60\\times0.196+0.6\\times60\\times15.71=671.5.$$\n\n**Answer.** $671.5\\,\\text{kN}$",
      "archetype": "C"
    },
    {
      "id": "ce-fe-013",
      "subject": "Foundation Engineering",
      "topic": "Active Thrust",
      "difficulty": "hard",
      "marks": 2,
      "type": "NAT",
      "stem": "A smooth vertical wall retains cohesionless soil ($\\phi=34^\\circ$, $\\gamma=18\\,\\text{kN/m}^3$) to height $5\\,\\text{m}$. The total active thrust per metre is _____ kN/m.",
      "answer": 63.61085693649885,
      "tolerance": 0.2,
      "solution": "**Concept.** $P_a=\\tfrac12K_a\\gamma H^2$.\n\n**Working.**\n$$K_a=0.283,\\ P_a=0.5\\times0.283\\times18\\times5^2=63.61.$$\n\n**Answer.** $63.61\\,\\text{kN/m}$",
      "archetype": "C"
    },
    {
      "id": "ce-fe-014",
      "subject": "Foundation Engineering",
      "topic": "Pile Capacity — Clay",
      "difficulty": "hard",
      "marks": 2,
      "type": "NAT",
      "stem": "A bored pile $0.5\\,\\text{m}$ dia, $10\\,\\text{m}$ long in clay ($c=50\\,\\text{kPa}$, $N_c=9$, $\\alpha=0.6$). Its ultimate capacity (end + skin) is _____ kN.",
      "answer": 559.5961914206819,
      "tolerance": 1,
      "solution": "**Concept.** $Q_u=9cA_p+\\alpha c A_s$.\n\n**Working.**\n$$9\\times50\\times0.196+0.6\\times50\\times15.71=559.6.$$\n\n**Answer.** $559.6\\,\\text{kN}$",
      "archetype": "C"
    },
    {
      "id": "ce-fe-015",
      "subject": "Foundation Engineering",
      "topic": "Terzaghi Bearing Capacity",
      "difficulty": "hard",
      "marks": 2,
      "type": "NAT",
      "stem": "Strip footing at $1\\,\\text{m}$ on clay: $c=20\\,\\text{kPa}$, $\\phi=0$, $\\gamma=16$. Terzaghi $q_u$ ($N_c=5.7,N_q=1,N_\\gamma=0$) is _____ kPa.",
      "answer": 130,
      "tolerance": 1,
      "solution": "**Concept.** $q_u=cN_c+\\gamma D_f$.\n\n**Working.**\n$$20\\times5.7+16\\times1=130.$$\n\n**Answer.** $130$",
      "archetype": "C"
    },
    {
      "id": "ce-fe-016",
      "subject": "Foundation Engineering",
      "topic": "Net Safe Bearing Capacity",
      "difficulty": "hard",
      "marks": 2,
      "type": "NAT",
      "stem": "Ultimate bearing capacity $300\\,\\text{kPa}$ at depth $2\\,\\text{m}$ ($\\gamma=18\\,\\text{kN/m}^3$), FoS $3$. The net safe bearing capacity is _____ kPa.",
      "answer": 88,
      "tolerance": 0.5,
      "solution": "**Concept.** $q_{ns}=\\dfrac{q_u-\\gamma D_f}{F}$.\n\n**Working.**\n$$\\dfrac{300-18\\times2}{3}=88.$$\n\n**Answer.** $88\\,\\text{kPa}$",
      "archetype": "C"
    },
    {
      "id": "ce-fe-017",
      "subject": "Foundation Engineering",
      "topic": "Terzaghi Bearing Capacity",
      "difficulty": "hard",
      "marks": 2,
      "type": "NAT",
      "stem": "Strip footing at $1.5\\,\\text{m}$ on clay: $c=30\\,\\text{kPa}$, $\\phi=0$, $\\gamma=18$. Terzaghi $q_u$ ($N_c=5.7,N_q=1,N_\\gamma=0$) is _____ kPa.",
      "answer": 198,
      "tolerance": 1,
      "solution": "**Concept.** $q_u=cN_c+\\gamma D_f$.\n\n**Working.**\n$$30\\times5.7+18\\times1.5=198.$$\n\n**Answer.** $198$",
      "archetype": "C"
    },
    {
      "id": "ce-fe-018",
      "subject": "Foundation Engineering",
      "topic": "Net Safe Bearing Capacity",
      "difficulty": "hard",
      "marks": 2,
      "type": "NAT",
      "stem": "Ultimate bearing capacity $500\\,\\text{kPa}$ at depth $1\\,\\text{m}$ ($\\gamma=20\\,\\text{kN/m}^3$), FoS $3$. The net safe bearing capacity is _____ kPa.",
      "answer": 160,
      "tolerance": 0.5,
      "solution": "**Concept.** $q_{ns}=\\dfrac{q_u-\\gamma D_f}{F}$.\n\n**Working.**\n$$\\dfrac{500-20\\times1}{3}=160.$$\n\n**Answer.** $160\\,\\text{kPa}$",
      "archetype": "C"
    },
    {
      "id": "ce-fe-019",
      "subject": "Foundation Engineering",
      "topic": "Net Safe Bearing Capacity",
      "difficulty": "hard",
      "marks": 2,
      "type": "NAT",
      "stem": "Ultimate bearing capacity $300\\,\\text{kPa}$ at depth $1\\,\\text{m}$ ($\\gamma=18\\,\\text{kN/m}^3$), FoS $3$. The net safe bearing capacity is _____ kPa.",
      "answer": 94,
      "tolerance": 0.5,
      "solution": "**Concept.** $q_{ns}=\\dfrac{q_u-\\gamma D_f}{F}$.\n\n**Working.**\n$$\\dfrac{300-18\\times1}{3}=94.$$\n\n**Answer.** $94\\,\\text{kPa}$",
      "archetype": "C"
    },
    {
      "id": "ce-fe-020",
      "subject": "Foundation Engineering",
      "topic": "Safe Bearing Capacity",
      "difficulty": "easy",
      "marks": 1,
      "type": "NAT",
      "stem": "Ultimate bearing capacity $300\\,\\text{kPa}$, FoS $3$. Safe bearing capacity is _____ kPa.",
      "answer": 100,
      "tolerance": 0.1,
      "solution": "**Concept.** $q_{safe}=q_u/\\text{FoS}$.\n\n**Working.**\n$$\\dfrac{300}{3}=100.$$\n\n**Answer.** $100$",
      "archetype": "A"
    },
    {
      "id": "ce-fe-021",
      "subject": "Foundation Engineering",
      "topic": "Pile Group Capacity",
      "difficulty": "medium",
      "marks": 2,
      "type": "NAT",
      "stem": "A group of $4$ piles (each $300\\,\\text{kN}$) has group efficiency $0.85$. The group capacity is _____ kN.",
      "answer": 1020,
      "tolerance": 1,
      "solution": "**Concept.** $Q_g=n\\,Q_{single}\\,\\eta$.\n\n**Working.**\n$$4\\times300\\times0.85=1020.$$\n\n**Answer.** $1020\\,\\text{kN}$",
      "archetype": "A"
    },
    {
      "id": "ce-fe-022",
      "subject": "Foundation Engineering",
      "topic": "Active Thrust",
      "difficulty": "hard",
      "marks": 2,
      "type": "NAT",
      "stem": "A smooth vertical wall retains cohesionless soil ($\\phi=34^\\circ$, $\\gamma=16\\,\\text{kN/m}^3$) to height $5\\,\\text{m}$. The total active thrust per metre is _____ kN/m.",
      "answer": 56.54298394355454,
      "tolerance": 0.2,
      "solution": "**Concept.** $P_a=\\tfrac12K_a\\gamma H^2$.\n\n**Working.**\n$$K_a=0.283,\\ P_a=0.5\\times0.283\\times16\\times5^2=56.54.$$\n\n**Answer.** $56.54\\,\\text{kN/m}$",
      "archetype": "C"
    },
    {
      "id": "ce-fe-023",
      "subject": "Foundation Engineering",
      "topic": "Bearing Pressure",
      "difficulty": "medium",
      "marks": 1,
      "type": "NAT",
      "stem": "Gross pressure $240\\,\\text{kPa}$ at depth $1\\,\\text{m}$, $\\gamma=18\\,\\text{kN/m}^3$. Net pressure is _____ kPa.",
      "answer": 222,
      "tolerance": 0.1,
      "solution": "**Concept.** $q_{net}=q-\\gamma D_f$.\n\n**Working.**\n$$240-18\\times1=222.$$\n\n**Answer.** $222\\,\\text{kPa}$",
      "archetype": "A"
    },
    {
      "id": "ce-fe-024",
      "subject": "Foundation Engineering",
      "topic": "Pile Capacity — Clay",
      "difficulty": "hard",
      "marks": 2,
      "type": "NAT",
      "stem": "A bored pile $0.4\\,\\text{m}$ dia, $15\\,\\text{m}$ long in clay ($c=60\\,\\text{kPa}$, $N_c=9$, $\\alpha=0.6$). Its ultimate capacity (end + skin) is _____ kN.",
      "answer": 746.4424144929349,
      "tolerance": 1,
      "solution": "**Concept.** $Q_u=9cA_p+\\alpha c A_s$.\n\n**Working.**\n$$9\\times60\\times0.126+0.6\\times60\\times18.85=746.4.$$\n\n**Answer.** $746.4\\,\\text{kN}$",
      "archetype": "C"
    },
    {
      "id": "ce-fe-025",
      "subject": "Foundation Engineering",
      "topic": "Active Thrust",
      "difficulty": "hard",
      "marks": 2,
      "type": "NAT",
      "stem": "A smooth vertical wall retains cohesionless soil ($\\phi=30^\\circ$, $\\gamma=20\\,\\text{kN/m}^3$) to height $6\\,\\text{m}$. The total active thrust per metre is _____ kN/m.",
      "answer": 120,
      "tolerance": 0.2,
      "solution": "**Concept.** $P_a=\\tfrac12K_a\\gamma H^2$.\n\n**Working.**\n$$K_a=0.333,\\ P_a=0.5\\times0.333\\times20\\times6^2=120.$$\n\n**Answer.** $120\\,\\text{kN/m}$",
      "archetype": "C"
    },
    {
      "id": "ce-fe-026",
      "subject": "Foundation Engineering",
      "topic": "Pile Capacity — Clay",
      "difficulty": "hard",
      "marks": 2,
      "type": "NAT",
      "stem": "A bored pile $0.5\\,\\text{m}$ dia, $12\\,\\text{m}$ long in clay ($c=40\\,\\text{kPa}$, $N_c=9$, $\\alpha=0.6$). Its ultimate capacity (end + skin) is _____ kN.",
      "answer": 523.0751768227005,
      "tolerance": 1,
      "solution": "**Concept.** $Q_u=9cA_p+\\alpha c A_s$.\n\n**Working.**\n$$9\\times40\\times0.196+0.6\\times40\\times18.85=523.1.$$\n\n**Answer.** $523.1\\,\\text{kN}$",
      "archetype": "C"
    },
    {
      "id": "ce-fe-027",
      "subject": "Foundation Engineering",
      "topic": "Pile Group Capacity",
      "difficulty": "medium",
      "marks": 2,
      "type": "NAT",
      "stem": "A group of $16$ piles (each $400\\,\\text{kN}$) has group efficiency $0.8$. The group capacity is _____ kN.",
      "answer": 5120,
      "tolerance": 1,
      "solution": "**Concept.** $Q_g=n\\,Q_{single}\\,\\eta$.\n\n**Working.**\n$$16\\times400\\times0.8=5120.$$\n\n**Answer.** $5120\\,\\text{kN}$",
      "archetype": "A"
    },
    {
      "id": "ce-fe-028",
      "subject": "Foundation Engineering",
      "topic": "Terzaghi Bearing Capacity",
      "difficulty": "hard",
      "marks": 2,
      "type": "NAT",
      "stem": "Strip footing at $1\\,\\text{m}$ on clay: $c=20\\,\\text{kPa}$, $\\phi=0$, $\\gamma=20$. Terzaghi $q_u$ ($N_c=5.7,N_q=1,N_\\gamma=0$) is _____ kPa.",
      "answer": 134,
      "tolerance": 1,
      "solution": "**Concept.** $q_u=cN_c+\\gamma D_f$.\n\n**Working.**\n$$20\\times5.7+20\\times1=134.$$\n\n**Answer.** $134$",
      "archetype": "C"
    },
    {
      "id": "ce-fe-029",
      "subject": "Foundation Engineering",
      "topic": "Active Thrust",
      "difficulty": "hard",
      "marks": 2,
      "type": "NAT",
      "stem": "A smooth vertical wall retains cohesionless soil ($\\phi=30^\\circ$, $\\gamma=18\\,\\text{kN/m}^3$) to height $5\\,\\text{m}$. The total active thrust per metre is _____ kN/m.",
      "answer": 75,
      "tolerance": 0.2,
      "solution": "**Concept.** $P_a=\\tfrac12K_a\\gamma H^2$.\n\n**Working.**\n$$K_a=0.333,\\ P_a=0.5\\times0.333\\times18\\times5^2=75.$$\n\n**Answer.** $75\\,\\text{kN/m}$",
      "archetype": "C"
    },
    {
      "id": "ce-fe-030",
      "subject": "Foundation Engineering",
      "topic": "Pile Group Capacity",
      "difficulty": "medium",
      "marks": 2,
      "type": "NAT",
      "stem": "A group of $16$ piles (each $300\\,\\text{kN}$) has group efficiency $0.7$. The group capacity is _____ kN.",
      "answer": 3360,
      "tolerance": 1,
      "solution": "**Concept.** $Q_g=n\\,Q_{single}\\,\\eta$.\n\n**Working.**\n$$16\\times300\\times0.7=3360.$$\n\n**Answer.** $3360\\,\\text{kN}$",
      "archetype": "A"
    },
    {
      "id": "ce-fe-031",
      "subject": "Foundation Engineering",
      "topic": "Active Thrust",
      "difficulty": "hard",
      "marks": 2,
      "type": "NAT",
      "stem": "A smooth vertical wall retains cohesionless soil ($\\phi=34^\\circ$, $\\gamma=20\\,\\text{kN/m}^3$) to height $4\\,\\text{m}$. The total active thrust per metre is _____ kN/m.",
      "answer": 45.23438715484363,
      "tolerance": 0.2,
      "solution": "**Concept.** $P_a=\\tfrac12K_a\\gamma H^2$.\n\n**Working.**\n$$K_a=0.283,\\ P_a=0.5\\times0.283\\times20\\times4^2=45.23.$$\n\n**Answer.** $45.23\\,\\text{kN/m}$",
      "archetype": "C"
    },
    {
      "id": "ce-fe-032",
      "subject": "Foundation Engineering",
      "topic": "Safe Bearing Capacity",
      "difficulty": "easy",
      "marks": 1,
      "type": "NAT",
      "stem": "Ultimate bearing capacity $540\\,\\text{kPa}$, FoS $3$. Safe bearing capacity is _____ kPa.",
      "answer": 180,
      "tolerance": 0.1,
      "solution": "**Concept.** $q_{safe}=q_u/\\text{FoS}$.\n\n**Working.**\n$$\\dfrac{540}{3}=180.$$\n\n**Answer.** $180$",
      "archetype": "A"
    },
    {
      "id": "ce-fe-033",
      "subject": "Foundation Engineering",
      "topic": "Pile Group Capacity",
      "difficulty": "medium",
      "marks": 2,
      "type": "NAT",
      "stem": "A group of $16$ piles (each $200\\,\\text{kN}$) has group efficiency $0.8$. The group capacity is _____ kN.",
      "answer": 2560,
      "tolerance": 1,
      "solution": "**Concept.** $Q_g=n\\,Q_{single}\\,\\eta$.\n\n**Working.**\n$$16\\times200\\times0.8=2560.$$\n\n**Answer.** $2560\\,\\text{kN}$",
      "archetype": "A"
    },
    {
      "id": "ce-fe-034",
      "subject": "Foundation Engineering",
      "topic": "Pile Group Capacity",
      "difficulty": "medium",
      "marks": 2,
      "type": "NAT",
      "stem": "A group of $4$ piles (each $200\\,\\text{kN}$) has group efficiency $0.7$. The group capacity is _____ kN.",
      "answer": 560,
      "tolerance": 1,
      "solution": "**Concept.** $Q_g=n\\,Q_{single}\\,\\eta$.\n\n**Working.**\n$$4\\times200\\times0.7=560.$$\n\n**Answer.** $560\\,\\text{kN}$",
      "archetype": "A"
    },
    {
      "id": "ce-fe-035",
      "subject": "Foundation Engineering",
      "topic": "Bearing Pressure",
      "difficulty": "medium",
      "marks": 1,
      "type": "NAT",
      "stem": "Gross pressure $180\\,\\text{kPa}$ at depth $1.5\\,\\text{m}$, $\\gamma=20\\,\\text{kN/m}^3$. Net pressure is _____ kPa.",
      "answer": 150,
      "tolerance": 0.1,
      "solution": "**Concept.** $q_{net}=q-\\gamma D_f$.\n\n**Working.**\n$$180-20\\times1.5=150.$$\n\n**Answer.** $150\\,\\text{kPa}$",
      "archetype": "A"
    },
    {
      "id": "ce-fe-036",
      "subject": "Foundation Engineering",
      "topic": "Net Safe Bearing Capacity",
      "difficulty": "hard",
      "marks": 2,
      "type": "NAT",
      "stem": "Ultimate bearing capacity $400\\,\\text{kPa}$ at depth $1\\,\\text{m}$ ($\\gamma=20\\,\\text{kN/m}^3$), FoS $3$. The net safe bearing capacity is _____ kPa.",
      "answer": 126.66666666666667,
      "tolerance": 0.5,
      "solution": "**Concept.** $q_{ns}=\\dfrac{q_u-\\gamma D_f}{F}$.\n\n**Working.**\n$$\\dfrac{400-20\\times1}{3}=126.7.$$\n\n**Answer.** $126.7\\,\\text{kPa}$",
      "archetype": "C"
    },
    {
      "id": "ce-fe-037",
      "subject": "Foundation Engineering",
      "topic": "Pile Group Capacity",
      "difficulty": "medium",
      "marks": 2,
      "type": "NAT",
      "stem": "A group of $9$ piles (each $200\\,\\text{kN}$) has group efficiency $0.8$. The group capacity is _____ kN.",
      "answer": 1440,
      "tolerance": 1,
      "solution": "**Concept.** $Q_g=n\\,Q_{single}\\,\\eta$.\n\n**Working.**\n$$9\\times200\\times0.8=1440.$$\n\n**Answer.** $1440\\,\\text{kN}$",
      "archetype": "A"
    },
    {
      "id": "ce-fe-038",
      "subject": "Foundation Engineering",
      "topic": "Pile Group Capacity",
      "difficulty": "medium",
      "marks": 2,
      "type": "NAT",
      "stem": "A group of $4$ piles (each $400\\,\\text{kN}$) has group efficiency $0.7$. The group capacity is _____ kN.",
      "answer": 1120,
      "tolerance": 1,
      "solution": "**Concept.** $Q_g=n\\,Q_{single}\\,\\eta$.\n\n**Working.**\n$$4\\times400\\times0.7=1120.$$\n\n**Answer.** $1120\\,\\text{kN}$",
      "archetype": "A"
    },
    {
      "id": "ce-fe-039",
      "subject": "Foundation Engineering",
      "topic": "Pile Group Capacity",
      "difficulty": "medium",
      "marks": 2,
      "type": "NAT",
      "stem": "A group of $9$ piles (each $400\\,\\text{kN}$) has group efficiency $0.8$. The group capacity is _____ kN.",
      "answer": 2880,
      "tolerance": 1,
      "solution": "**Concept.** $Q_g=n\\,Q_{single}\\,\\eta$.\n\n**Working.**\n$$9\\times400\\times0.8=2880.$$\n\n**Answer.** $2880\\,\\text{kN}$",
      "archetype": "A"
    },
    {
      "id": "ce-fe-040",
      "subject": "Foundation Engineering",
      "topic": "Active Thrust",
      "difficulty": "hard",
      "marks": 2,
      "type": "NAT",
      "stem": "A smooth vertical wall retains cohesionless soil ($\\phi=30^\\circ$, $\\gamma=18\\,\\text{kN/m}^3$) to height $4\\,\\text{m}$. The total active thrust per metre is _____ kN/m.",
      "answer": 48,
      "tolerance": 0.2,
      "solution": "**Concept.** $P_a=\\tfrac12K_a\\gamma H^2$.\n\n**Working.**\n$$K_a=0.333,\\ P_a=0.5\\times0.333\\times18\\times4^2=48.$$\n\n**Answer.** $48\\,\\text{kN/m}$",
      "archetype": "C"
    },
    {
      "id": "ce-fe-041",
      "subject": "Foundation Engineering",
      "topic": "Bearing Pressure",
      "difficulty": "medium",
      "marks": 1,
      "type": "NAT",
      "stem": "Gross pressure $240\\,\\text{kPa}$ at depth $2\\,\\text{m}$, $\\gamma=16\\,\\text{kN/m}^3$. Net pressure is _____ kPa.",
      "answer": 208,
      "tolerance": 0.1,
      "solution": "**Concept.** $q_{net}=q-\\gamma D_f$.\n\n**Working.**\n$$240-16\\times2=208.$$\n\n**Answer.** $208\\,\\text{kPa}$",
      "archetype": "A"
    },
    {
      "id": "ce-fe-042",
      "subject": "Foundation Engineering",
      "topic": "Active Thrust",
      "difficulty": "hard",
      "marks": 2,
      "type": "NAT",
      "stem": "A smooth vertical wall retains cohesionless soil ($\\phi=30^\\circ$, $\\gamma=16\\,\\text{kN/m}^3$) to height $5\\,\\text{m}$. The total active thrust per metre is _____ kN/m.",
      "answer": 66.66666666666666,
      "tolerance": 0.2,
      "solution": "**Concept.** $P_a=\\tfrac12K_a\\gamma H^2$.\n\n**Working.**\n$$K_a=0.333,\\ P_a=0.5\\times0.333\\times16\\times5^2=66.67.$$\n\n**Answer.** $66.67\\,\\text{kN/m}$",
      "archetype": "C"
    },
    {
      "id": "ce-fe-043",
      "subject": "Foundation Engineering",
      "topic": "Bearing Pressure",
      "difficulty": "medium",
      "marks": 1,
      "type": "NAT",
      "stem": "Gross pressure $180\\,\\text{kPa}$ at depth $1\\,\\text{m}$, $\\gamma=20\\,\\text{kN/m}^3$. Net pressure is _____ kPa.",
      "answer": 160,
      "tolerance": 0.1,
      "solution": "**Concept.** $q_{net}=q-\\gamma D_f$.\n\n**Working.**\n$$180-20\\times1=160.$$\n\n**Answer.** $160\\,\\text{kPa}$",
      "archetype": "A"
    },
    {
      "id": "ce-fe-044",
      "subject": "Foundation Engineering",
      "topic": "Earth Pressure — Passive",
      "difficulty": "medium",
      "marks": 2,
      "type": "NAT",
      "stem": "For a cohesionless soil with $\\phi=30^\\circ$, the Rankine passive earth pressure coefficient $K_p$ is _____.",
      "answer": 3,
      "tolerance": 0.01,
      "solution": "**Concept.** $K_p=\\dfrac{1+\\sin\\phi}{1-\\sin\\phi}$.\n\n**Working.**\n$$\\dfrac{1+\\sin30^\\circ}{1-\\sin30^\\circ}=3.$$\n\n**Answer.** $3$",
      "archetype": "A"
    },
    {
      "id": "ce-fe-045",
      "subject": "Foundation Engineering",
      "topic": "Terzaghi Bearing Capacity",
      "difficulty": "hard",
      "marks": 2,
      "type": "NAT",
      "stem": "Strip footing at $1.5\\,\\text{m}$ on clay: $c=20\\,\\text{kPa}$, $\\phi=0$, $\\gamma=18$. Terzaghi $q_u$ ($N_c=5.7,N_q=1,N_\\gamma=0$) is _____ kPa.",
      "answer": 141,
      "tolerance": 1,
      "solution": "**Concept.** $q_u=cN_c+\\gamma D_f$.\n\n**Working.**\n$$20\\times5.7+18\\times1.5=141.$$\n\n**Answer.** $141$",
      "archetype": "C"
    },
    {
      "id": "ce-fe-046",
      "subject": "Foundation Engineering",
      "topic": "Net Safe Bearing Capacity",
      "difficulty": "hard",
      "marks": 2,
      "type": "NAT",
      "stem": "Ultimate bearing capacity $400\\,\\text{kPa}$ at depth $2\\,\\text{m}$ ($\\gamma=20\\,\\text{kN/m}^3$), FoS $3$. The net safe bearing capacity is _____ kPa.",
      "answer": 120,
      "tolerance": 0.5,
      "solution": "**Concept.** $q_{ns}=\\dfrac{q_u-\\gamma D_f}{F}$.\n\n**Working.**\n$$\\dfrac{400-20\\times2}{3}=120.$$\n\n**Answer.** $120\\,\\text{kPa}$",
      "archetype": "C"
    },
    {
      "id": "ce-fe-047",
      "subject": "Foundation Engineering",
      "topic": "Active Thrust",
      "difficulty": "hard",
      "marks": 2,
      "type": "NAT",
      "stem": "A smooth vertical wall retains cohesionless soil ($\\phi=34^\\circ$, $\\gamma=18\\,\\text{kN/m}^3$) to height $4\\,\\text{m}$. The total active thrust per metre is _____ kN/m.",
      "answer": 40.710948439359264,
      "tolerance": 0.2,
      "solution": "**Concept.** $P_a=\\tfrac12K_a\\gamma H^2$.\n\n**Working.**\n$$K_a=0.283,\\ P_a=0.5\\times0.283\\times18\\times4^2=40.71.$$\n\n**Answer.** $40.71\\,\\text{kN/m}$",
      "archetype": "C"
    },
    {
      "id": "ce-fe-048",
      "subject": "Foundation Engineering",
      "topic": "Pile Group Capacity",
      "difficulty": "medium",
      "marks": 2,
      "type": "NAT",
      "stem": "A group of $9$ piles (each $300\\,\\text{kN}$) has group efficiency $0.7$. The group capacity is _____ kN.",
      "answer": 1889.9999999999998,
      "tolerance": 1,
      "solution": "**Concept.** $Q_g=n\\,Q_{single}\\,\\eta$.\n\n**Working.**\n$$9\\times300\\times0.7=1890.$$\n\n**Answer.** $1890\\,\\text{kN}$",
      "archetype": "A"
    },
    {
      "id": "ce-fe-049",
      "subject": "Foundation Engineering",
      "topic": "Pile Group Capacity",
      "difficulty": "medium",
      "marks": 2,
      "type": "NAT",
      "stem": "A group of $9$ piles (each $200\\,\\text{kN}$) has group efficiency $0.7$. The group capacity is _____ kN.",
      "answer": 1260,
      "tolerance": 1,
      "solution": "**Concept.** $Q_g=n\\,Q_{single}\\,\\eta$.\n\n**Working.**\n$$9\\times200\\times0.7=1260.$$\n\n**Answer.** $1260\\,\\text{kN}$",
      "archetype": "A"
    },
    {
      "id": "ce-fe-050",
      "subject": "Foundation Engineering",
      "topic": "Pile Capacity — Clay",
      "difficulty": "hard",
      "marks": 2,
      "type": "NAT",
      "stem": "A bored pile $0.5\\,\\text{m}$ dia, $15\\,\\text{m}$ long in clay ($c=60\\,\\text{kPa}$, $N_c=9$, $\\alpha=0.6$). Its ultimate capacity (end + skin) is _____ kN.",
      "answer": 954.2587685278996,
      "tolerance": 1,
      "solution": "**Concept.** $Q_u=9cA_p+\\alpha c A_s$.\n\n**Working.**\n$$9\\times60\\times0.196+0.6\\times60\\times23.56=954.3.$$\n\n**Answer.** $954.3\\,\\text{kN}$",
      "archetype": "C"
    },
    {
      "id": "ce-fe-051",
      "subject": "Foundation Engineering",
      "topic": "Active Thrust",
      "difficulty": "hard",
      "marks": 2,
      "type": "NAT",
      "stem": "A smooth vertical wall retains cohesionless soil ($\\phi=34^\\circ$, $\\gamma=16\\,\\text{kN/m}^3$) to height $4\\,\\text{m}$. The total active thrust per metre is _____ kN/m.",
      "answer": 36.1875097238749,
      "tolerance": 0.2,
      "solution": "**Concept.** $P_a=\\tfrac12K_a\\gamma H^2$.\n\n**Working.**\n$$K_a=0.283,\\ P_a=0.5\\times0.283\\times16\\times4^2=36.19.$$\n\n**Answer.** $36.19\\,\\text{kN/m}$",
      "archetype": "C"
    },
    {
      "id": "ce-fe-052",
      "subject": "Foundation Engineering",
      "topic": "Active Thrust",
      "difficulty": "hard",
      "marks": 2,
      "type": "NAT",
      "stem": "A smooth vertical wall retains cohesionless soil ($\\phi=30^\\circ$, $\\gamma=16\\,\\text{kN/m}^3$) to height $4\\,\\text{m}$. The total active thrust per metre is _____ kN/m.",
      "answer": 42.666666666666664,
      "tolerance": 0.2,
      "solution": "**Concept.** $P_a=\\tfrac12K_a\\gamma H^2$.\n\n**Working.**\n$$K_a=0.333,\\ P_a=0.5\\times0.333\\times16\\times4^2=42.67.$$\n\n**Answer.** $42.67\\,\\text{kN/m}$",
      "archetype": "C"
    },
    {
      "id": "ce-fe-053",
      "subject": "Foundation Engineering",
      "topic": "Pile Capacity — Clay",
      "difficulty": "hard",
      "marks": 2,
      "type": "NAT",
      "stem": "A bored pile $0.4\\,\\text{m}$ dia, $10\\,\\text{m}$ long in clay ($c=60\\,\\text{kPa}$, $N_c=9$, $\\alpha=0.6$). Its ultimate capacity (end + skin) is _____ kN.",
      "answer": 520.2477434344697,
      "tolerance": 1,
      "solution": "**Concept.** $Q_u=9cA_p+\\alpha c A_s$.\n\n**Working.**\n$$9\\times60\\times0.126+0.6\\times60\\times12.57=520.2.$$\n\n**Answer.** $520.2\\,\\text{kN}$",
      "archetype": "C"
    },
    {
      "id": "ce-fe-054",
      "subject": "Foundation Engineering",
      "topic": "Pile Group Capacity",
      "difficulty": "medium",
      "marks": 2,
      "type": "NAT",
      "stem": "A group of $9$ piles (each $400\\,\\text{kN}$) has group efficiency $0.7$. The group capacity is _____ kN.",
      "answer": 2520,
      "tolerance": 1,
      "solution": "**Concept.** $Q_g=n\\,Q_{single}\\,\\eta$.\n\n**Working.**\n$$9\\times400\\times0.7=2520.$$\n\n**Answer.** $2520\\,\\text{kN}$",
      "archetype": "A"
    },
    {
      "id": "ce-fe-055",
      "subject": "Foundation Engineering",
      "topic": "Pile Group Capacity",
      "difficulty": "medium",
      "marks": 2,
      "type": "NAT",
      "stem": "A group of $9$ piles (each $200\\,\\text{kN}$) has group efficiency $0.85$. The group capacity is _____ kN.",
      "answer": 1530,
      "tolerance": 1,
      "solution": "**Concept.** $Q_g=n\\,Q_{single}\\,\\eta$.\n\n**Working.**\n$$9\\times200\\times0.85=1530.$$\n\n**Answer.** $1530\\,\\text{kN}$",
      "archetype": "A"
    },
    {
      "id": "ce-fe-056",
      "subject": "Foundation Engineering",
      "topic": "Bearing Pressure",
      "difficulty": "medium",
      "marks": 1,
      "type": "NAT",
      "stem": "Gross pressure $200\\,\\text{kPa}$ at depth $1.5\\,\\text{m}$, $\\gamma=16\\,\\text{kN/m}^3$. Net pressure is _____ kPa.",
      "answer": 176,
      "tolerance": 0.1,
      "solution": "**Concept.** $q_{net}=q-\\gamma D_f$.\n\n**Working.**\n$$200-16\\times1.5=176.$$\n\n**Answer.** $176\\,\\text{kPa}$",
      "archetype": "A"
    },
    {
      "id": "ce-fe-057",
      "subject": "Foundation Engineering",
      "topic": "Earth Pressure — Passive",
      "difficulty": "medium",
      "marks": 2,
      "type": "NAT",
      "stem": "For a cohesionless soil with $\\phi=34^\\circ$, the Rankine passive earth pressure coefficient $K_p$ is _____.",
      "answer": 3.537132037454109,
      "tolerance": 0.01,
      "solution": "**Concept.** $K_p=\\dfrac{1+\\sin\\phi}{1-\\sin\\phi}$.\n\n**Working.**\n$$\\dfrac{1+\\sin34^\\circ}{1-\\sin34^\\circ}=3.537.$$\n\n**Answer.** $3.537$",
      "archetype": "A"
    },
    {
      "id": "ce-fe-058",
      "subject": "Foundation Engineering",
      "topic": "Safe Bearing Capacity",
      "difficulty": "easy",
      "marks": 1,
      "type": "NAT",
      "stem": "Ultimate bearing capacity $450\\,\\text{kPa}$, FoS $3$. Safe bearing capacity is _____ kPa.",
      "answer": 150,
      "tolerance": 0.1,
      "solution": "**Concept.** $q_{safe}=q_u/\\text{FoS}$.\n\n**Working.**\n$$\\dfrac{450}{3}=150.$$\n\n**Answer.** $150$",
      "archetype": "A"
    },
    {
      "id": "ce-fe-059",
      "subject": "Foundation Engineering",
      "topic": "Terzaghi Bearing Capacity",
      "difficulty": "hard",
      "marks": 2,
      "type": "NAT",
      "stem": "Strip footing at $1\\,\\text{m}$ on clay: $c=40\\,\\text{kPa}$, $\\phi=0$, $\\gamma=18$. Terzaghi $q_u$ ($N_c=5.7,N_q=1,N_\\gamma=0$) is _____ kPa.",
      "answer": 246,
      "tolerance": 1,
      "solution": "**Concept.** $q_u=cN_c+\\gamma D_f$.\n\n**Working.**\n$$40\\times5.7+18\\times1=246.$$\n\n**Answer.** $246$",
      "archetype": "C"
    },
    {
      "id": "ce-fe-060",
      "subject": "Foundation Engineering",
      "topic": "Terzaghi Bearing Capacity",
      "difficulty": "hard",
      "marks": 2,
      "type": "NAT",
      "stem": "Strip footing at $1.5\\,\\text{m}$ on clay: $c=40\\,\\text{kPa}$, $\\phi=0$, $\\gamma=20$. Terzaghi $q_u$ ($N_c=5.7,N_q=1,N_\\gamma=0$) is _____ kPa.",
      "answer": 258,
      "tolerance": 1,
      "solution": "**Concept.** $q_u=cN_c+\\gamma D_f$.\n\n**Working.**\n$$40\\times5.7+20\\times1.5=258.$$\n\n**Answer.** $258$",
      "archetype": "C"
    },
    {
      "id": "ce-fe-061",
      "subject": "Foundation Engineering",
      "topic": "Bearing Pressure",
      "difficulty": "medium",
      "marks": 1,
      "type": "NAT",
      "stem": "Gross pressure $300\\,\\text{kPa}$ at depth $1.5\\,\\text{m}$, $\\gamma=18\\,\\text{kN/m}^3$. Net pressure is _____ kPa.",
      "answer": 273,
      "tolerance": 0.1,
      "solution": "**Concept.** $q_{net}=q-\\gamma D_f$.\n\n**Working.**\n$$300-18\\times1.5=273.$$\n\n**Answer.** $273\\,\\text{kPa}$",
      "archetype": "A"
    },
    {
      "id": "ce-fe-062",
      "subject": "Foundation Engineering",
      "topic": "Net Safe Bearing Capacity",
      "difficulty": "hard",
      "marks": 2,
      "type": "NAT",
      "stem": "Ultimate bearing capacity $300\\,\\text{kPa}$ at depth $1.5\\,\\text{m}$ ($\\gamma=20\\,\\text{kN/m}^3$), FoS $3$. The net safe bearing capacity is _____ kPa.",
      "answer": 90,
      "tolerance": 0.5,
      "solution": "**Concept.** $q_{ns}=\\dfrac{q_u-\\gamma D_f}{F}$.\n\n**Working.**\n$$\\dfrac{300-20\\times1.5}{3}=90.$$\n\n**Answer.** $90\\,\\text{kPa}$",
      "archetype": "C"
    },
    {
      "id": "ce-fe-063",
      "subject": "Foundation Engineering",
      "topic": "Pile Group Capacity",
      "difficulty": "medium",
      "marks": 2,
      "type": "NAT",
      "stem": "A group of $16$ piles (each $300\\,\\text{kN}$) has group efficiency $0.85$. The group capacity is _____ kN.",
      "answer": 4080,
      "tolerance": 1,
      "solution": "**Concept.** $Q_g=n\\,Q_{single}\\,\\eta$.\n\n**Working.**\n$$16\\times300\\times0.85=4080.$$\n\n**Answer.** $4080\\,\\text{kN}$",
      "archetype": "A"
    },
    {
      "id": "ce-fe-064",
      "subject": "Foundation Engineering",
      "topic": "Pile Group Capacity",
      "difficulty": "medium",
      "marks": 2,
      "type": "NAT",
      "stem": "A group of $9$ piles (each $400\\,\\text{kN}$) has group efficiency $0.85$. The group capacity is _____ kN.",
      "answer": 3060,
      "tolerance": 1,
      "solution": "**Concept.** $Q_g=n\\,Q_{single}\\,\\eta$.\n\n**Working.**\n$$9\\times400\\times0.85=3060.$$\n\n**Answer.** $3060\\,\\text{kN}$",
      "archetype": "A"
    },
    {
      "id": "ce-fe-065",
      "subject": "Foundation Engineering",
      "topic": "Terzaghi Bearing Capacity",
      "difficulty": "hard",
      "marks": 2,
      "type": "NAT",
      "stem": "Strip footing at $1.5\\,\\text{m}$ on clay: $c=40\\,\\text{kPa}$, $\\phi=0$, $\\gamma=16$. Terzaghi $q_u$ ($N_c=5.7,N_q=1,N_\\gamma=0$) is _____ kPa.",
      "answer": 252,
      "tolerance": 1,
      "solution": "**Concept.** $q_u=cN_c+\\gamma D_f$.\n\n**Working.**\n$$40\\times5.7+16\\times1.5=252.$$\n\n**Answer.** $252$",
      "archetype": "C"
    },
    {
      "id": "ce-fe-066",
      "subject": "Foundation Engineering",
      "topic": "Pile Capacity — Clay",
      "difficulty": "hard",
      "marks": 2,
      "type": "NAT",
      "stem": "A bored pile $0.5\\,\\text{m}$ dia, $12\\,\\text{m}$ long in clay ($c=60\\,\\text{kPa}$, $N_c=9$, $\\alpha=0.6$). Its ultimate capacity (end + skin) is _____ kN.",
      "answer": 784.6127652340508,
      "tolerance": 1,
      "solution": "**Concept.** $Q_u=9cA_p+\\alpha c A_s$.\n\n**Working.**\n$$9\\times60\\times0.196+0.6\\times60\\times18.85=784.6.$$\n\n**Answer.** $784.6\\,\\text{kN}$",
      "archetype": "C"
    },
    {
      "id": "ce-fe-067",
      "subject": "Foundation Engineering",
      "topic": "Net Safe Bearing Capacity",
      "difficulty": "hard",
      "marks": 2,
      "type": "NAT",
      "stem": "Ultimate bearing capacity $500\\,\\text{kPa}$ at depth $1.5\\,\\text{m}$ ($\\gamma=20\\,\\text{kN/m}^3$), FoS $3$. The net safe bearing capacity is _____ kPa.",
      "answer": 156.66666666666666,
      "tolerance": 0.5,
      "solution": "**Concept.** $q_{ns}=\\dfrac{q_u-\\gamma D_f}{F}$.\n\n**Working.**\n$$\\dfrac{500-20\\times1.5}{3}=156.7.$$\n\n**Answer.** $156.7\\,\\text{kPa}$",
      "archetype": "C"
    },
    {
      "id": "ce-fe-068",
      "subject": "Foundation Engineering",
      "topic": "Pile Capacity — Clay",
      "difficulty": "hard",
      "marks": 2,
      "type": "NAT",
      "stem": "A bored pile $0.4\\,\\text{m}$ dia, $10\\,\\text{m}$ long in clay ($c=50\\,\\text{kPa}$, $N_c=9$, $\\alpha=0.6$). Its ultimate capacity (end + skin) is _____ kN.",
      "answer": 433.53978619539146,
      "tolerance": 1,
      "solution": "**Concept.** $Q_u=9cA_p+\\alpha c A_s$.\n\n**Working.**\n$$9\\times50\\times0.126+0.6\\times50\\times12.57=433.5.$$\n\n**Answer.** $433.5\\,\\text{kN}$",
      "archetype": "C"
    },
    {
      "id": "ce-fe-069",
      "subject": "Foundation Engineering",
      "topic": "Terzaghi Bearing Capacity",
      "difficulty": "hard",
      "marks": 2,
      "type": "NAT",
      "stem": "Strip footing at $1\\,\\text{m}$ on clay: $c=30\\,\\text{kPa}$, $\\phi=0$, $\\gamma=18$. Terzaghi $q_u$ ($N_c=5.7,N_q=1,N_\\gamma=0$) is _____ kPa.",
      "answer": 189,
      "tolerance": 1,
      "solution": "**Concept.** $q_u=cN_c+\\gamma D_f$.\n\n**Working.**\n$$30\\times5.7+18\\times1=189.$$\n\n**Answer.** $189$",
      "archetype": "C"
    },
    {
      "id": "ce-fe-070",
      "subject": "Foundation Engineering",
      "topic": "Bearing Pressure",
      "difficulty": "medium",
      "marks": 1,
      "type": "NAT",
      "stem": "Gross pressure $300\\,\\text{kPa}$ at depth $1\\,\\text{m}$, $\\gamma=18\\,\\text{kN/m}^3$. Net pressure is _____ kPa.",
      "answer": 282,
      "tolerance": 0.1,
      "solution": "**Concept.** $q_{net}=q-\\gamma D_f$.\n\n**Working.**\n$$300-18\\times1=282.$$\n\n**Answer.** $282\\,\\text{kPa}$",
      "archetype": "A"
    },
    {
      "id": "ce-fe-071",
      "subject": "Foundation Engineering",
      "topic": "Active Thrust",
      "difficulty": "hard",
      "marks": 2,
      "type": "NAT",
      "stem": "A smooth vertical wall retains cohesionless soil ($\\phi=34^\\circ$, $\\gamma=16\\,\\text{kN/m}^3$) to height $6\\,\\text{m}$. The total active thrust per metre is _____ kN/m.",
      "answer": 81.42189687871853,
      "tolerance": 0.2,
      "solution": "**Concept.** $P_a=\\tfrac12K_a\\gamma H^2$.\n\n**Working.**\n$$K_a=0.283,\\ P_a=0.5\\times0.283\\times16\\times6^2=81.42.$$\n\n**Answer.** $81.42\\,\\text{kN/m}$",
      "archetype": "C"
    },
    {
      "id": "ce-fe-072",
      "subject": "Foundation Engineering",
      "topic": "Bearing Pressure",
      "difficulty": "medium",
      "marks": 1,
      "type": "NAT",
      "stem": "Gross pressure $300\\,\\text{kPa}$ at depth $1.5\\,\\text{m}$, $\\gamma=16\\,\\text{kN/m}^3$. Net pressure is _____ kPa.",
      "answer": 276,
      "tolerance": 0.1,
      "solution": "**Concept.** $q_{net}=q-\\gamma D_f$.\n\n**Working.**\n$$300-16\\times1.5=276.$$\n\n**Answer.** $276\\,\\text{kPa}$",
      "archetype": "A"
    },
    {
      "id": "ce-fe-073",
      "subject": "Foundation Engineering",
      "topic": "Bearing Pressure",
      "difficulty": "medium",
      "marks": 1,
      "type": "NAT",
      "stem": "Gross pressure $240\\,\\text{kPa}$ at depth $1.5\\,\\text{m}$, $\\gamma=18\\,\\text{kN/m}^3$. Net pressure is _____ kPa.",
      "answer": 213,
      "tolerance": 0.1,
      "solution": "**Concept.** $q_{net}=q-\\gamma D_f$.\n\n**Working.**\n$$240-18\\times1.5=213.$$\n\n**Answer.** $213\\,\\text{kPa}$",
      "archetype": "A"
    },
    {
      "id": "ce-fe-074",
      "subject": "Foundation Engineering",
      "topic": "Bearing Pressure",
      "difficulty": "medium",
      "marks": 1,
      "type": "NAT",
      "stem": "Gross pressure $180\\,\\text{kPa}$ at depth $2\\,\\text{m}$, $\\gamma=20\\,\\text{kN/m}^3$. Net pressure is _____ kPa.",
      "answer": 140,
      "tolerance": 0.1,
      "solution": "**Concept.** $q_{net}=q-\\gamma D_f$.\n\n**Working.**\n$$180-20\\times2=140.$$\n\n**Answer.** $140\\,\\text{kPa}$",
      "archetype": "A"
    },
    {
      "id": "ce-fe-075",
      "subject": "Foundation Engineering",
      "topic": "Pile Capacity — Clay",
      "difficulty": "hard",
      "marks": 2,
      "type": "NAT",
      "stem": "A bored pile $0.4\\,\\text{m}$ dia, $10\\,\\text{m}$ long in clay ($c=40\\,\\text{kPa}$, $N_c=9$, $\\alpha=0.6$). Its ultimate capacity (end + skin) is _____ kN.",
      "answer": 346.8318289563132,
      "tolerance": 1,
      "solution": "**Concept.** $Q_u=9cA_p+\\alpha c A_s$.\n\n**Working.**\n$$9\\times40\\times0.126+0.6\\times40\\times12.57=346.8.$$\n\n**Answer.** $346.8\\,\\text{kN}$",
      "archetype": "C"
    },
    {
      "id": "ce-fe-076",
      "subject": "Foundation Engineering",
      "topic": "Bearing Pressure",
      "difficulty": "medium",
      "marks": 1,
      "type": "NAT",
      "stem": "Gross pressure $180\\,\\text{kPa}$ at depth $2\\,\\text{m}$, $\\gamma=16\\,\\text{kN/m}^3$. Net pressure is _____ kPa.",
      "answer": 148,
      "tolerance": 0.1,
      "solution": "**Concept.** $q_{net}=q-\\gamma D_f$.\n\n**Working.**\n$$180-16\\times2=148.$$\n\n**Answer.** $148\\,\\text{kPa}$",
      "archetype": "A"
    },
    {
      "id": "ce-fe-077",
      "subject": "Foundation Engineering",
      "topic": "Bearing Pressure",
      "difficulty": "medium",
      "marks": 1,
      "type": "NAT",
      "stem": "Gross pressure $200\\,\\text{kPa}$ at depth $1\\,\\text{m}$, $\\gamma=16\\,\\text{kN/m}^3$. Net pressure is _____ kPa.",
      "answer": 184,
      "tolerance": 0.1,
      "solution": "**Concept.** $q_{net}=q-\\gamma D_f$.\n\n**Working.**\n$$200-16\\times1=184.$$\n\n**Answer.** $184\\,\\text{kPa}$",
      "archetype": "A"
    },
    {
      "id": "ce-fe-078",
      "subject": "Foundation Engineering",
      "topic": "Terzaghi Bearing Capacity",
      "difficulty": "hard",
      "marks": 2,
      "type": "NAT",
      "stem": "Strip footing at $1\\,\\text{m}$ on clay: $c=40\\,\\text{kPa}$, $\\phi=0$, $\\gamma=16$. Terzaghi $q_u$ ($N_c=5.7,N_q=1,N_\\gamma=0$) is _____ kPa.",
      "answer": 244,
      "tolerance": 1,
      "solution": "**Concept.** $q_u=cN_c+\\gamma D_f$.\n\n**Working.**\n$$40\\times5.7+16\\times1=244.$$\n\n**Answer.** $244$",
      "archetype": "C"
    }
  ]
}
